{"cameraMode":{"drawMode":0,"name":"Shaded","section":"Shading Mode"},"sceneLighting":true,"audioPlay":false,"sceneViewState":{"showFog":true,"showMaterialUpdate":false,"showSkybox":true,"showFlares":true,"showImageEffects":true,"showParticleSystems":true},"in2DMode":false,"pivot":{"x":0.16184350848197938,"y":-0.10420829057693482,"z":0.5898367762565613},"rotation":{"x":0.47621023654937746,"y":-0.07739832252264023,"z":0.041905373334884647,"w":0.875175416469574},"size":0.9401562809944153,"orthographic":false}